github_issue_creator/__init__.py
github_issue_creator/issue_creator.py
pygithub_assist-0.1.0.dist-info/LICENSE
pygithub_assist-0.1.0.dist-info/METADATA
pygithub_assist-0.1.0.dist-info/WHEEL
pygithub_assist-0.1.0.dist-info/top_level.txt
pygithub_assist-0.1.0.dist-info/RECORD
