Metadata-Version: 2.1
Name: pygithub-assist
Version: 0.1.0
Summary: Internal package to automatically create GitHub issues
Author: Lokesh
Requires-Python: >=3.8
License-File: LICENSE
Requires-Dist: PyGithub>=2.1.0
